fem_matrix_1D_2Dtq_3D/__init__.py
fem_matrix_1D_2Dtq_3D/fem_matrix_1D_2Dtq_3D.py
fem_matrix_1D_2Dtq_3D-0.0.2.dist-info/LICENSE.txt
fem_matrix_1D_2Dtq_3D-0.0.2.dist-info/METADATA
fem_matrix_1D_2Dtq_3D-0.0.2.dist-info/WHEEL
fem_matrix_1D_2Dtq_3D-0.0.2.dist-info/top_level.txt
fem_matrix_1D_2Dtq_3D-0.0.2.dist-info/RECORD
