Metadata-Version: 2.1
Name: fem_matrix_1D_2Dtq_3D
Version: 0.0.2
Summary: Package with functions to create mass and stiffness matrix for the FEM method
Home-page: https://github.com/dmorencos/fem_matrix_1D_2Dtq_3D
Author: Diego Morencos Pazos
Author-email: diegomorencos3@gmail.com
Classifier: Programming Language :: Python :: 3
Classifier: License :: OSI Approved :: MIT License
Classifier: Operating System :: OS Independent
Requires-Python: >=3.7
License-File: LICENSE.txt
Requires-Dist: numpy
Requires-Dist: scipy
